pytest_motor/__init__.py
pytest_motor/mongod_binary.py
pytest_motor/plugin.py
pytest_motor-0.3.0.dist-info/LICENSE.txt
pytest_motor-0.3.0.dist-info/METADATA
pytest_motor-0.3.0.dist-info/WHEEL
pytest_motor-0.3.0.dist-info/entry_points.txt
pytest_motor-0.3.0.dist-info/top_level.txt
pytest_motor-0.3.0.dist-info/RECORD
