Metadata-Version: 2.1
Name: pytest-motor
Version: 0.3.0
Summary: A pytest plugin for motor, the non-blocking MongoDB driver.
Home-page: https://github.com/AustinScola/pytest-motor
Author: Austin Scola
Author-email: austinscola@gmail.com
License: UNKNOWN
Platform: UNKNOWN
Classifier: Development Status :: 3 - Alpha
Classifier: Programming Language :: Python :: 3.6
Classifier: License :: OSI Approved :: MIT License
Classifier: Operating System :: OS Independent
Classifier: Framework :: Pytest
Classifier: Topic :: Software Development :: Testing
Classifier: Typing :: Typed
Requires-Python: >=3.6
License-File: LICENSE.txt
Requires-Dist: pytest
Requires-Dist: motor
Requires-Dist: aiohttp[speedups]
Requires-Dist: distro
